UserResponseCollector/UserQueryCommand.py
UserResponseCollector/UserQueryReceiver.py
UserResponseCollector/__init__.py
UserResponseCollector/main.py
userresponsecollector-1.1.0.dist-info/METADATA
userresponsecollector-1.1.0.dist-info/WHEEL
userresponsecollector-1.1.0.dist-info/entry_points.txt
userresponsecollector-1.1.0.dist-info/licenses/LICENSE
userresponsecollector-1.1.0.dist-info/RECORD
