Metadata-Version: 2.4
Name: UserResponseCollector
Version: 1.1.0
Summary: UserResponseCollector facilitates the collection of user responses from the command line.
Keywords: query,console,input,response
Author-Email: "Kevin R. Geurts" <kevin.r.geurts@gmail.com>
License-Expression: MIT
License-File: LICENSE
Classifier: Programming Language :: Python :: 3
Classifier: Operating System :: OS Independent
Classifier: Development Status :: 5 - Production/Stable
Classifier: Environment :: Console
Classifier: Intended Audience :: Developers
Classifier: Topic :: Software Development :: Libraries :: Python Modules
Classifier: Topic :: Software Development :: User Interfaces
Project-URL: Homepage, https://github.com/KevinRGeurts/UserResponseCollector
Project-URL: Issues, https://github.com/KevinRGeurts/UserResponseCollector/issues
Requires-Python: >=3.12
